kookit/__init__.py
kookit/client_side.py
kookit/http_kookit/__init__.py
kookit/http_kookit/interfaces.py
kookit/http_kookit/kookit.py
kookit/http_kookit/models/__init__.py
kookit/http_kookit/models/json_request.py
kookit/http_kookit/models/json_response.py
kookit/http_kookit/models/request.py
kookit/http_kookit/models/response.py
kookit/http_kookit/models/utils.py
kookit/http_kookit/models/xml_response.py
kookit/http_kookit/response_group.py
kookit/http_kookit/server.py
kookit/http_kookit/service.py
kookit/interfaces.py
kookit/kookit.py
kookit/logging.py
kookit/py.typed
kookit/utils.py
pytest_kookit-0.1.4.dist-info/METADATA
pytest_kookit-0.1.4.dist-info/WHEEL
pytest_kookit-0.1.4.dist-info/entry_points.txt
pytest_kookit-0.1.4.dist-info/RECORD
